gryds/__init__.py
gryds/config.py
gryds/utils.py
gryds/interpolators/__init__.py
gryds/interpolators/base.py
gryds/interpolators/bspline.py
gryds/interpolators/color.py
gryds/interpolators/cuda.py
gryds/interpolators/grid.py
gryds/interpolators/linear.py
gryds/transformers/__init__.py
gryds/transformers/affine.py
gryds/transformers/base.py
gryds/transformers/bspline.py
gryds/transformers/composed.py
gryds/transformers/cuda.py
gryds/transformers/linear.py
gryds/transformers/translation.py
gryds-0.0.9.dist-info/LICENSE
gryds-0.0.9.dist-info/METADATA
gryds-0.0.9.dist-info/WHEEL
gryds-0.0.9.dist-info/top_level.txt
gryds-0.0.9.dist-info/RECORD
