Metadata-Version: 2.1
Name: gryds
Version: 0.0.9
Summary: Gryds: a Python package for geometric transformations of images
Home-page: https://github.com/MBPhys/gryds
Author: Marc Boucsein, Robin Koch
License: UNKNOWN
Platform: UNKNOWN
Classifier: Programming Language :: Python :: 3
Classifier: License :: OSI Approved :: GNU General Public License v3 (GPLv3)
Classifier: Operating System :: OS Independent
License-File: LICENSE
Requires-Dist: scipy
Requires-Dist: numpy
